pms_driver/__init__.py
pms_driver/__version__.py
pms_driver/cli.py
pms_driver/send2pms.py
pms_driver/suite.py
pms_driver/task.py
pms_driver-2024.9.18.dist-info/METADATA
pms_driver-2024.9.18.dist-info/WHEEL
pms_driver-2024.9.18.dist-info/entry_points.txt
pms_driver-2024.9.18.dist-info/licenses/LICENSE
pms_driver-2024.9.18.dist-info/RECORD
