Metadata-Version: 2.1
Name: pms-driver
Version: 2024.9.18
Author-email: mikigo <huangmingqiang@uniontech.com>
License: GPL2.0
License-File: LICENSE
Requires-Python: >=3.7
Requires-Dist: click
Requires-Dist: funnylog2
Requires-Dist: requests
